{"Jia Wang":{"27717":{"name":"Hardware/Software Codesign","crn":"27717","course":"ECE 587","section":"01","link":"https://ssb.iit.edu/bnrprd/bwckschd.p_disp_detail_sched?term_in=202020&crn_in=27717","term":"Spring 2020","registration":"No dates available","levels":"Graduate Business, Graduate, Undergraduate","attributes":"Standard Tuition Rate","campus":"Mies Campus","type":"Lecture","instructional_method":"Traditional Instructional Method","credits":3,"catalog":"https://ssb.iit.edu/bnrprd/bwckctlg.p_display_courses?term_in=202020&one_subj=ECE&sel_crse_strt=587&sel_crse_end=587&sel_subj=&sel_levl=&sel_schd=&sel_coll=&sel_divs=&sel_dept=&sel_attr=","instructors":["Jia Wang"],"dateRange":"Jan 13, 2020 - May 09, 2020","classes":{"T":{"start":1020,"end":1095,"location":"TBA"},"R":{"start":1020,"end":1095,"location":"TBA"}}}}}
