{"Brian Casario":{"13211":{"name":"Cross-Cultural Comm I Lab","crn":"13211","course":"IDN 464","section":"01","link":"https://ssb.iit.edu/bnrprd/bwckschd.p_disp_detail_sched?term_in=202010&crn_in=13211","term":"Fall 2019","registration":"Apr 23, 2019 to Aug 31, 2019","levels":"Graduate Business, Graduate, Undergraduate","attributes":"ID Tuition Rate","campus":"Mies Campus","type":"Lab","instructional_method":"Traditional Instructional Method","credits":1,"catalog":"https://ssb.iit.edu/bnrprd/bwckctlg.p_display_courses?term_in=202010&one_subj=IDN&sel_crse_strt=464&sel_crse_end=464&sel_subj=&sel_levl=&sel_schd=&sel_coll=&sel_divs=&sel_dept=&sel_attr=","instructors":["Brian Casario"],"dateRange":"Aug 19, 2019 - Dec 07, 2019","classes":{"F":{"start":840,"end":1020,"location":"Ed Kaplan Family Institute 223"}}}}}
