{"Santosh Basapur":{"26461":{"name":"Modes of Human Experience","crn":"26461","course":"IDX 508","section":"01","link":"https://ssb.iit.edu/bnrprd/bwckschd.p_disp_detail_sched?term_in=202020&crn_in=26461","term":"Spring 2020","registration":"No dates available","levels":"Graduate","attributes":"ID Tuition Rate","campus":"Mies Campus","type":"Lecture","instructional_method":"Traditional Instructional Method","credits":1,"catalog":"https://ssb.iit.edu/bnrprd/bwckctlg.p_display_courses?term_in=202020&one_subj=IDX&sel_crse_strt=508&sel_crse_end=508&sel_subj=&sel_levl=&sel_schd=&sel_coll=&sel_divs=&sel_dept=&sel_attr=","instructors":["Santosh Basapur"],"dateRange":"Mar 23, 2020 - May 09, 2020","classes":{"M":{"start":1080,"end":1260,"location":"Ed Kaplan Family Institute 226"}}}}}
