{"Thomas Andrew Johnson":{"50344":{"name":"Incident Response, Disaster Recovery, and Business Continuity","crn":"50344","course":"ITMS 588","section":"01","link":"https://ssb.iit.edu/bnrprd/bwckschd.p_disp_detail_sched?term_in=202020&crn_in=50344","term":"Spring 2020","registration":"Nov 04, 2019 to Jan 25, 2020","levels":"Graduate, Undergraduate","attributes":"Standard Tuition Rate","campus":"Mies Campus","type":"Lecture","instructional_method":"Traditional Instructional Method","credits":3,"catalog":"https://ssb.iit.edu/bnrprd/bwckctlg.p_display_courses?term_in=202020&one_subj=ITMS&sel_crse_strt=588&sel_crse_end=588&sel_subj=&sel_levl=&sel_schd=&sel_coll=&sel_divs=&sel_dept=&sel_attr=","instructors":["Thomas Andrew Johnson"],"dateRange":"Jan 13, 2020 - May 09, 2020","classes":{"T":{"start":1105,"end":1265,"location":"Stuart Building 212"}}}}}
