{"Jenifer M Robbins":{"51681":{"name":"Business Organizations","crn":"51681","course":"LAW 409","section":"01","link":"https://ssb.iit.edu/bnrprd/bwckschd.p_disp_detail_sched?term_in=202020&crn_in=51681","term":"Spring 2020","registration":"Dec 03, 2019 to Feb 03, 2020","levels":"Graduate Business, Master of Laws, Law","attributes":"CK Law Tuition Rate","campus":"Downtown Campus","type":"Lecture","instructional_method":"Traditional Instructional Method","credits":4,"catalog":"https://ssb.iit.edu/bnrprd/bwckctlg.p_display_courses?term_in=202020&one_subj=LAW&sel_crse_strt=409&sel_crse_end=409&sel_subj=&sel_levl=&sel_schd=&sel_coll=&sel_divs=&sel_dept=&sel_attr=","instructors":["Jenifer M Robbins"],"dateRange":"Jan 21, 2020 - Apr 30, 2020","classes":{"T":{"start":840,"end":950,"location":"TBA"},"R":{"start":840,"end":950,"location":"TBA"}}}},"Ronald S. Gieseke":{"51724":{"name":"Business Organizations","crn":"51724","course":"LAW 409","section":"51","link":"https://ssb.iit.edu/bnrprd/bwckschd.p_disp_detail_sched?term_in=202020&crn_in=51724","term":"Spring 2020","registration":"Dec 03, 2019 to Feb 03, 2020","levels":"Graduate Business, Master of Laws, Law","attributes":"CK Law Tuition Rate","campus":"Downtown Campus","type":"Lecture","instructional_method":"Traditional Instructional Method","credits":4,"catalog":"https://ssb.iit.edu/bnrprd/bwckctlg.p_display_courses?term_in=202020&one_subj=LAW&sel_crse_strt=409&sel_crse_end=409&sel_subj=&sel_levl=&sel_schd=&sel_coll=&sel_divs=&sel_dept=&sel_attr=","instructors":["Ronald S. Gieseke"],"dateRange":"Jan 21, 2020 - Apr 30, 2020","classes":{"M":{"start":1050,"end":1160,"location":"Downtown Campus 510"},"W":{"start":1050,"end":1160,"location":"Downtown Campus 510"}}}}}
